Metadata-Version: 1.0
Name: dgood-gabinodist
Version: 0.3
Summary: Gaussian and binomial distributions
Home-page: UNKNOWN
Author: UNKNOWN
Author-email: UNKNOWN
License: UNKNOWN
Platform: UNKNOWN
